radiation_toolbox_reader/__init__.py
radiation_toolbox_reader/ers.csv
radiation_toolbox_reader/ers.py
radiation_toolbox_reader/exceptions.py
radiation_toolbox_reader/logger.py
radiation_toolbox_reader/pei.csv
radiation_toolbox_reader/pei.py
radiation_toolbox_reader/safecast.csv
radiation_toolbox_reader/safecast.py
radiation_toolbox_reader/utils.py
radiation_toolbox_reader-1.0.2.dist-info/licenses/LICENSE
radiation_toolbox_reader-1.0.2.dist-info/METADATA
radiation_toolbox_reader-1.0.2.dist-info/WHEEL
radiation_toolbox_reader-1.0.2.dist-info/top_level.txt
radiation_toolbox_reader-1.0.2.dist-info/RECORD
