Metadata-Version: 2.4
Name: radiation-toolbox-reader
Version: 1.0.2
Summary: Radiation Toolbox Reader
Author-email: Martin Landa <martin.landa@opengeolabs.cz>
License: GPLv3
Project-URL: documentation, https://opengeolabs.gitlab.io/radiation-toolbox/radiation-toolbox-reader/
Project-URL: repository, https://gitlab.com/opengeolabs/radiation-toolbox/radiation-toolbox-reader
Requires-Python: >=3.9
License-File: LICENSE
Requires-Dist: python-dateutil
Requires-Dist: pyproj
Requires-Dist: gdal>=3.8
Dynamic: license-file
